combmodel/__init__.py
combmodel/combmodel.py
comb_model-1.0.1.dist-info/LICENSE.rst
comb_model-1.0.1.dist-info/METADATA
comb_model-1.0.1.dist-info/WHEEL
comb_model-1.0.1.dist-info/top_level.txt
comb_model-1.0.1.dist-info/RECORD
