Metadata-Version: 2.1
Name: comb-model
Version: 1.0.1
Summary: A package to simulate Fractional Brownian walks on a comb-like structure.
Home-page: https://github.com/lgaalves/CombModel
Author: Luiz G. A. Alves
Author-email: "Luiz G. A. Alves" <lgaalves@northwestern.edu>
License: MIT
Platform: UNKNOWN
Classifier: Programming Language :: Python :: 3
Classifier: License :: OSI Approved :: MIT License
Classifier: Operating System :: OS Independent
Requires-Dist: stochastic
Requires-Dist: numpy
Requires-Dist: tqdm
